metapan/__init__.py
metapan/metapan.py
metapan/modules/__init__.py
metapan/modules/combiner.py
metapan/modules/panning.py
metapan/modules/utility.py
metapan/statsmodules/__init__.py
metapan-0.0.5.dist-info/LICENSE
metapan-0.0.5.dist-info/METADATA
metapan-0.0.5.dist-info/WHEEL
metapan-0.0.5.dist-info/entry_points.txt
metapan-0.0.5.dist-info/top_level.txt
metapan-0.0.5.dist-info/zip-safe
metapan-0.0.5.dist-info/RECORD
