Metadata-Version: 2.1
Name: metapan
Version: 0.0.5
Summary: Start
Home-page: https://github.com/AnupamGautam/metapan.git
Author: Anupam Gautam
Author-email: gautamanupam07@gmail.com
License: GPL
Keywords: pangenome on metagenome
Platform: UNKNOWN
Classifier: Programming Language :: Python :: 3.8
Classifier: Operating System :: OS Independent
